AUTHORS
CHANGELOG.md
CONTRIBUTING.md
LICENSE
MANIFEST.in
README.md
setup.py
deckhand/__about__.py
deckhand/__init__.py
deckhand/__main__.py
deckhand.egg-info/PKG-INFO
deckhand.egg-info/SOURCES.txt
deckhand.egg-info/dependency_links.txt
deckhand.egg-info/entry_points.txt
deckhand.egg-info/requires.txt
deckhand.egg-info/top_level.txt
deckhand/commands/__init__.py
deckhand/commands/configure.py
deckhand/commands/install.py
deckhand/commands/list.py
deckhand/commands/update.py
deckhand/util/__init__.py
deckhand/util/logger.py
deckhand/util/pip.py