Metadata-Version: 2.1
Name: deckhand
Version: 1.0.1
Summary: A Collection of development tools
Home-page: https://oceanstack.io/toolkit/deckhand
Author: The Deckhand Authors
Author-email: staff@oceanstack.io
License: Apache License 2.0
Keywords: deckhand oceanstack development
Platform: UNKNOWN
Classifier: Topic :: Software Development :: Build Tools
Classifier: Topic :: System :: Archiving :: Packaging
Classifier: Topic :: System :: Software Distribution
Classifier: Development Status :: 5 - Production/Stable
Classifier: License :: OSI Approved :: Apache Software License
Classifier: Programming Language :: Python :: 3 :: Only
Classifier: Operating System :: OS Independent
Classifier: Environment :: Console
Classifier: Intended Audience :: Developers
Classifier: Natural Language :: English
Requires-Python: >=3.0.*, <4
